mcp_server_neo4j_gds/__init__.py
mcp_server_neo4j_gds/algorithm_handler.py
mcp_server_neo4j_gds/centrality_algorithm_handlers.py
mcp_server_neo4j_gds/centrality_algorithm_specs.py
mcp_server_neo4j_gds/community_algorithm_handlers.py
mcp_server_neo4j_gds/community_algorithm_specs.py
mcp_server_neo4j_gds/gds.py
mcp_server_neo4j_gds/node_translator.py
mcp_server_neo4j_gds/path_algorithm_handlers.py
mcp_server_neo4j_gds/path_algorithm_specs.py
mcp_server_neo4j_gds/registry.py
mcp_server_neo4j_gds/server.py
mcp_server_neo4j_gds/similarity_algorithm_handlers.py
mcp_server_neo4j_gds/similarity_algorithm_specs.py
gds_agent-0.4.0.dist-info/METADATA
gds_agent-0.4.0.dist-info/WHEEL
gds_agent-0.4.0.dist-info/entry_points.txt
gds_agent-0.4.0.dist-info/RECORD
