Metadata-Version: 2.4
Name: gds-agent
Version: 0.4.0
Summary: Neo4j GDS MCP Server
Project-URL: Homepage, https://github.com/neo4j-contrib/gds-agent
License: MIT
Keywords: graph,graph algorithms,graph data science,mcp,neo4j
Classifier: Intended Audience :: Developers
Classifier: License :: OSI Approved :: MIT License
Classifier: Programming Language :: Python :: 3
Classifier: Programming Language :: Python :: 3.11
Classifier: Programming Language :: Python :: 3.12
Requires-Python: >=3.11
Requires-Dist: graphdatascience>=1.16
Requires-Dist: mcp[cli]>=1.11.0
